simplestate/__init__.py
simplestate/state.py
simplestate/state_machine.py
simplestate-0.1.5.dist-info/LICENSE
simplestate-0.1.5.dist-info/METADATA
simplestate-0.1.5.dist-info/WHEEL
simplestate-0.1.5.dist-info/RECORD
