Metadata-Version: 2.1
Name: simplestate
Version: 0.1.5
Summary: A simple stupid, declarative finite state machine for Python.
Home-page: https://pypi.org/project/simplestate
License: Apache-2.0
Keywords: finite state machine,simplestate
Author: panupong-puttarathamrongkul
Author-email: 54784627+panupong-puttarathamrongkul@users.noreply.github.com
Requires-Python: >=3.10,<4.0
Classifier: License :: OSI Approved :: Apache Software License
Classifier: Programming Language :: Python :: 3
Classifier: Programming Language :: Python :: 3.10
Classifier: Programming Language :: Python :: 3.11
Classifier: Programming Language :: Python :: 3.12
Classifier: Topic :: Software Development :: Libraries :: Python Modules
Project-URL: Repository, https://github.com/panupong-develop/simplestate
